setup.py
src/dt_motion_planning/__init__.py
src/dt_motion_planning/lane_controller/__init__.py
src/dt_motion_planning/lane_controller/lane_controller.py
src/dt_motion_planning/lane_controller/types.py
src/lib_dt_motion_planning.egg-info/PKG-INFO
src/lib_dt_motion_planning.egg-info/SOURCES.txt
src/lib_dt_motion_planning.egg-info/dependency_links.txt
src/lib_dt_motion_planning.egg-info/requires.txt
src/lib_dt_motion_planning.egg-info/top_level.txt